kalong/__init__.py
kalong/__main__.py
kalong/communication.py
kalong/config.py
kalong/debugger.py
kalong/errors.py
kalong/forking.py
kalong/loops.py
kalong/server.py
kalong/stepping.py
kalong/tracing.py
kalong/websockets.py
kalong/static/index.html
kalong/static/assets/FiraCode-Bold-DzhvDiv4.woff2
kalong/static/assets/FiraCode-Regular-jAL9VymT.woff2
kalong/static/assets/favicon-rdSYpj7B.svg
kalong/static/assets/index-BQBgymAp.js
kalong/utils/__init__.py
kalong/utils/io.py
kalong/utils/iterators.py
kalong/utils/obj.py
kalong/utils/doc_lookup/__init__.py
kalong/utils/doc_lookup/lookup.json
kalong-0.8.0.dist-info/METADATA
kalong-0.8.0.dist-info/WHEEL
kalong-0.8.0.dist-info/entry_points.txt
kalong-0.8.0.dist-info/licenses/LICENSE
kalong-0.8.0.dist-info/RECORD
