Metadata-Version: 2.4
Name: kalong
Version: 0.8.0
Summary: A new take on python debugging
Author-email: Florian Mounier <paradoxxx.zero@gmail.com>
License-Expression: GPL-3.0-or-later
License-File: LICENSE
Keywords: debugger
Classifier: Development Status :: 4 - Beta
Classifier: Environment :: Console
Classifier: Intended Audience :: End Users/Desktop
Classifier: License :: OSI Approved :: GNU General Public License v3 or later (GPLv3+)
Classifier: Operating System :: OS Independent
Classifier: Programming Language :: Python :: 3
Requires-Python: >=3.8
Requires-Dist: aiohttp>=3.10.6
Requires-Dist: cutter>=0.5.0
Requires-Dist: jedi>=0.19.1
Provides-Extra: disassembly
Requires-Dist: uncompyle6>=3.9.2; extra == 'disassembly'
Provides-Extra: recursive
Requires-Dist: nest-asyncio>=1.6.0; extra == 'recursive'
